ttl_memoized.py
ttl_memoized-0.2.1.dist-info/DESCRIPTION.rst
ttl_memoized-0.2.1.dist-info/METADATA
ttl_memoized-0.2.1.dist-info/RECORD
ttl_memoized-0.2.1.dist-info/WHEEL
ttl_memoized-0.2.1.dist-info/metadata.json
ttl_memoized-0.2.1.dist-info/top_level.txt
