Metadata-Version: 2.0
Name: ttl-memoized
Version: 0.2.1
Summary: TTLMemoized - a memoized decorator with TTL (time-to-live) support
Home-page: http://github.com/tly1980/ttl_memoized
Author: Tom Tang
Author-email: tly1980@gmail.com
License: MIT
Platform: UNKNOWN
Classifier: Development Status :: 4 - Beta
Classifier: Environment :: Plugins
Classifier: Intended Audience :: Developers
Classifier: License :: OSI Approved :: MIT License
Classifier: Operating System :: OS Independent
Classifier: Programming Language :: Python :: 2.6
Classifier: Programming Language :: Python :: 2.7
Classifier: Programming Language :: Python :: 3.3
Classifier: Programming Language :: Python :: 3.4
Classifier: Programming Language :: Python :: 3.5
Classifier: Programming Language :: Python :: 3.6
